[
  {
  "id": "VÝSLEDEK SOUBOJE 1/16",
  "title": " |  | VÝSLEDEK SOUBOJE 1/16"
},
  {
  "id": "VOLNÝ POSTUP",
  "title": " |  | VOLNÝ POSTUP"
},
  {
    "id": "Daniel Bizinskyj",
    "title": "PHA | 14C | Daniel Bizinskyj"
  },
  {
    "id": "Jan Brož",
    "title": "LBK | 13B | Jan Brož"
  },
  {
    "id": "Vendelín Ňima Ciler",
    "title": "KHK | 11D | Vendelín Ňima Ciler"
  },
  {
    "id": "Maxim Hanzal",
    "title": "VYS | 17B | Maxim Hanzal"
  },
  {
    "id": "Kryštof Kaválek",
    "title": "MSK | 11C | Kryštof Kaválek"
  },
  {
    "id": "Štěpán Kincl",
    "title": "OLK | 14A | Štěpán Kincl"
  },
  {
    "id": "Štěpán Kopička",
    "title": "PLK | 15D | Štěpán Kopička"
  },
  {
    "id": "Tomáš Kočí",
    "title": "SCK | 17A | Tomáš Kočí"
  },
  {
    "id": "Tomáš Kučera",
    "title": "JMK | 12A | Tomáš Kučera"
  },
  {
    "id": "Rostislav Mašek",
    "title": "SCK | 15C | Rostislav Mašek"
  },
  {
    "id": "Ondřej Navrátil",
    "title": "ZLK | 17C | Ondřej Navrátil"
  },
  {
    "id": "Karel Novotný",
    "title": "KVK | 12B | Karel Novotný"
  },
  {
    "id": "Patrik Pirner",
    "title": "PLK | 16D | Patrik Pirner"
  },
  {
    "id": "Karel Rozehnal",
    "title": "OLK | 15A | Karel Rozehnal"
  },
  {
    "id": "Filip Skopal",
    "title": "ZLK | 16C | Filip Skopal"
  },
  {
    "id": "Jan Vachoušek",
    "title": "PHA | 13C | Jan Vachoušek"
  },
  {
    "id": "Viktor Valíček",
    "title": "KVK | 13A | Viktor Valíček"
  },
  {
    "id": "Tomáš Veselý",
    "title": "USK | 14B | Tomáš Veselý"
  },
  {
    "id": "Zdenek Vála",
    "title": "VYS | 16B | Zdenek Vála"
  },
  {
    "id": "Vojtěch Šimandl",
    "title": "MSK | 12C | Vojtěch Šimandl"
  },
  {
    "id": "Petr Škarek",
    "title": "JMK | 11A | Petr Škarek"
  },
  {
    "id": "Pavel Šmejkal",
    "title": "JČK | 10B | Pavel Šmejkal"
  },
  {
    "id": "Klára Fikrlová",
    "title": "PLK | 7C | Klára Fikrlová"
  },
  {
    "id": "Sofi Fucimanová",
    "title": "MSK | 6C | Sofi Fucimanová"
  },
  {
    "id": "Adéla Fučíková",
    "title": "JMK | 3B | Adéla Fučíková"
  },
  {
    "id": "Kristýna Hálová",
    "title": "VYS | 6B | Kristýna Hálová"
  },
  {
    "id": "Laura Kanclerová",
    "title": "JMK | 4A | Laura Kanclerová"
  },
  {
    "id": "Sofia Khikhlukha",
    "title": "PHA | 8A | Sofia Khikhlukha"
  },
  {
    "id": "Renata Klápová",
    "title": "SCK | 9D | Renata Klápová"
  },
  {
    "id": "Lucie Kočová",
    "title": "JČK | 3A | Lucie Kočová"
  },
  {
    "id": "Valerie Kubíčková",
    "title": "SCK | 8D | Valerie Kubíčková"
  },
  {
    "id": "Nina Kulovaná",
    "title": "PHA | 7A | Nina Kulovaná"
  },
  {
    "id": "Sarah Kurzweilová",
    "title": "KVK | 5A | Sarah Kurzweilová"
  },
  {
    "id": "Adéla Kuržejová",
    "title": "KVK | 6A | Adéla Kuržejová"
  },
  {
    "id": "Thea Malcharová",
    "title": "ZLK | 9C | Thea Malcharová"
  },
  {
    "id": "Elena Mlčochová",
    "title": "OLK | 5D | Elena Mlčochová"
  },
  {
    "id": "Magdaléna Mrkvová",
    "title": "MSK | 5C | Magdaléna Mrkvová"
  },
  {
    "id": "Kimi Nicolette Troják",
    "title": "USK | 9A | Kimi Nicolette Troják"
  },
  {
    "id": "Michaela Urbanová",
    "title": "USK | 10A | Michaela Urbanová"
  },
  {
    "id": "Michaela Velísková",
    "title": "ZLK | 10C | Michaela Velísková"
  },
  {
    "id": "Zuzana Votrubcová",
    "title": "LBK | 4C | Zuzana Votrubcová"
  },
  {
    "id": "Eliška Zajíčková",
    "title": "VYS | 7B | Eliška Zajíčková"
  },
  {
    "id": "Aneta Šinová",
    "title": "OLK | 4D | Aneta Šinová"
  },
  {
    "id": "Valerie Šitinová",
    "title": "LBK | 3C | Valerie Šitinová"
  },
  {
    "id": "Viktorie Šímová",
    "title": "PLK | 8C | Viktorie Šímová"
  }
]
